airflow_queue_stats/__init__.py
airflow_queue_stats/calculate.py
airflow_queue_stats/gather.py
airflow_queue_stats/models.py
airflow_queue_stats/plugin.py
airflow_queue_stats/views/__init__.py
airflow_queue_stats/views/api.py
airflow_queue_stats-0.1.4.dist-info/METADATA
airflow_queue_stats-0.1.4.dist-info/RECORD
airflow_queue_stats-0.1.4.dist-info/WHEEL
airflow_queue_stats-0.1.4.dist-info/entry_points.txt
airflow_queue_stats-0.1.4.dist-info/top_level.txt
